aiohttp_jrpc/__init__.py
aiohttp_jrpc/errors.py
aiohttp_jrpc/exc.py
aiohttp_jrpc-0.2.0.dist-info/licenses/AUTHORS.rst
aiohttp_jrpc-0.2.0.dist-info/licenses/LICENSE
aiohttp_jrpc-0.2.0.dist-info/METADATA
aiohttp_jrpc-0.2.0.dist-info/WHEEL
aiohttp_jrpc-0.2.0.dist-info/top_level.txt
aiohttp_jrpc-0.2.0.dist-info/RECORD
