Metadata-Version: 2.4
Name: aiohttp_jrpc
Version: 0.2.0
Summary: JSON RPC protocol for aiohttp.web (http server for asyncio)
Home-page: https://github.com/zloidemon/aiohttp_jrpc/
Author: Veniamin Gvozdikov
Author-email: g.veniamin@googlemail.com
License: BSD
Keywords: aiohttp jsonrpc rpc
Platform: any
Classifier: Intended Audience :: Developers
Classifier: License :: OSI Approved :: BSD License
Classifier: Programming Language :: Python :: 3
Classifier: Programming Language :: Python :: 3.11
Classifier: Programming Language :: Python :: 3.12
Classifier: Programming Language :: Python :: 3.13
Classifier: Programming Language :: Python
Classifier: Topic :: Internet :: WWW/HTTP
License-File: LICENSE
License-File: AUTHORS.rst
Requires-Dist: aiohttp>=3.12.14
Requires-Dist: jsonschema>=4.24.0
Dynamic: author
Dynamic: author-email
Dynamic: classifier
Dynamic: description
Dynamic: home-page
Dynamic: keywords
Dynamic: license
Dynamic: license-file
Dynamic: platform
Dynamic: requires-dist
Dynamic: summary
